pandas_tabulate/__init__.py
pandas_tabulate/core.py
pandas_tabulate/results.py
pandas_tabulate/stats.py
pandas_tabulate-0.1.0.dist-info/licenses/LICENSE
pandas_tabulate-0.1.0.dist-info/METADATA
pandas_tabulate-0.1.0.dist-info/WHEEL
pandas_tabulate-0.1.0.dist-info/top_level.txt
pandas_tabulate-0.1.0.dist-info/RECORD
