Metadata-Version: 2.4
Name: pandas-tabulate
Version: 0.1.0
Summary: Python implementation of Stata's tabulate command for pandas DataFrames
Author-email: Bryce Wang <brycew6m@stanford.edu>
Maintainer-email: Bryce Wang <brycew6m@stanford.edu>
License: MIT
Project-URL: Homepage, https://github.com/brycewang-stanford/pandas-tabulate
Project-URL: Documentation, https://github.com/brycewang-stanford/pandas-tabulate#readme
Project-URL: Repository, https://github.com/brycewang-stanford/pandas-tabulate
Project-URL: Bug Tracker, https://github.com/brycewang-stanford/pandas-tabulate/issues
Keywords: stata,tabulate,pandas,statistics,cross-tabulation
Classifier: Development Status :: 4 - Beta
Classifier: Intended Audience :: Science/Research
Classifier: License :: OSI Approved :: MIT License
Classifier: Operating System :: OS Independent
Classifier: Programming Language :: Python :: 3
Classifier: Programming Language :: Python :: 3.7
Classifier: Programming Language :: Python :: 3.8
Classifier: Programming Language :: Python :: 3.9
Classifier: Programming Language :: Python :: 3.10
Classifier: Programming Language :: Python :: 3.11
Classifier: Topic :: Scientific/Engineering
Classifier: Topic :: Scientific/Engineering :: Information Analysis
Requires-Python: >=3.7
License-File: LICENSE
Requires-Dist: pandas>=1.3.0
Requires-Dist: numpy>=1.20.0
Requires-Dist: scipy>=1.7.0
Provides-Extra: dev
Requires-Dist: pytest>=6.0; extra == "dev"
Requires-Dist: black>=22.0; extra == "dev"
Requires-Dist: flake8>=4.0; extra == "dev"
Requires-Dist: isort>=5.0; extra == "dev"
Dynamic: license-file
